serpent_image/__init__.py
serpent_image/image.py
serpentai_image-0.1.1.dist-info/LICENSE
serpentai_image-0.1.1.dist-info/WHEEL
serpentai_image-0.1.1.dist-info/METADATA
serpentai_image-0.1.1.dist-info/RECORD
